AUTHORS.rst
CHANGES.rst
LICENSE.rst
MANIFEST.in
README.rst
TODO.rst
setup.cfg
setup.py
birdhousebuilder/__init__.py
birdhousebuilder.recipe.r.egg-info/PKG-INFO
birdhousebuilder.recipe.r.egg-info/SOURCES.txt
birdhousebuilder.recipe.r.egg-info/dependency_links.txt
birdhousebuilder.recipe.r.egg-info/entry_points.txt
birdhousebuilder.recipe.r.egg-info/namespace_packages.txt
birdhousebuilder.recipe.r.egg-info/not-zip-safe
birdhousebuilder.recipe.r.egg-info/requires.txt
birdhousebuilder.recipe.r.egg-info/top_level.txt
birdhousebuilder/recipe/__init__.py
birdhousebuilder/recipe/r/__init__.py
birdhousebuilder/recipe/r/tests/__init__.py
birdhousebuilder/recipe/r/tests/test_docs.py