Metadata-Version: 1.1
Name: birdhousebuilder.recipe.r
Version: 0.1.3
Summary: A Buildout recipe to install R packages with Anaconda.
Home-page: http://www.dkrz.de
Author: Carsten Ehbrecht
Author-email: ehbrecht@dkrz.de
License: BSD
Keywords: buildout recipe
Platform: UNKNOWN
Classifier: Framework :: Buildout
Classifier: Intended Audience :: Developers
Classifier: Topic :: Software Development :: Build Tools
Classifier: Topic :: Software Development :: Libraries :: Python Modules
Classifier: License :: OSI Approved :: BSD License
